shared_memory_lock/__init__.py
shared_memory_lock/lock.py
shared_memory_lock/mutex.py
shared_memory_lock-0.1.5.dist-info/METADATA
shared_memory_lock-0.1.5.dist-info/WHEEL
shared_memory_lock-0.1.5.dist-info/top_level.txt
shared_memory_lock-0.1.5.dist-info/RECORD
