Metadata-Version: 2.4
Name: shared_memory_lock
Version: 0.1.5
Summary: A multiprocessing lock implemented using shared memory and atomics.
Author-email: Raymond Chastain <RaymondLC92@protonmail.com>
License: MIT
Keywords: multiprocessing,lock,synchronization,atomic,shared-memory
Classifier: Development Status :: 4 - Beta
Classifier: Intended Audience :: Developers
Classifier: License :: OSI Approved :: MIT License
Classifier: Programming Language :: Python :: 3
Classifier: Programming Language :: Python :: 3.13
Classifier: Topic :: Software Development :: Libraries :: Python Modules
Classifier: Topic :: System :: Hardware :: Symmetric Multi-processing
Requires-Python: >=3.13.7
Requires-Dist: atomics>=1.0.3
